split_settings/__init__.py
split_settings/py.typed
split_settings/tools.py
split_settings-1.0.0.dist-info/LICENSE
split_settings-1.0.0.dist-info/WHEEL
split_settings-1.0.0.dist-info/METADATA
split_settings-1.0.0.dist-info/RECORD
