Metadata-Version: 2.1
Name: split-settings
Version: 1.0.0
Summary: Organize Django settings into multiple files and directories. Easily override and modify settings. Use wildcards and optional settings files.
Home-page: https://django-split-settings.readthedocs.io
Author: sobolevn
Author-email: mail@sobolevn.me
Keywords: django,settings,configuration,config
Requires-Python: >=3.6,<4.0
Classifier: Development Status :: 5 - Production/Stable
Classifier: Environment :: Web Environment
Classifier: Framework :: Django
Classifier: Framework :: Django :: 1.11
Classifier: Framework :: Django :: 2.1
Classifier: Framework :: Django :: 2.2
Classifier: Intended Audience :: Developers
Classifier: License :: OSI Approved :: BSD License
Classifier: Operating System :: OS Independent
Classifier: Programming Language :: Python :: 3
Classifier: Programming Language :: Python :: 3.6
Classifier: Programming Language :: Python :: 3.7
Classifier: Topic :: Internet :: WWW/HTTP
Classifier: Topic :: Internet :: WWW/HTTP :: Dynamic Content
Classifier: Topic :: Software Development :: Libraries :: Python Modules
Project-URL: Repository, https://github.com/sobolevn/django-split-settings
